epquery/__init__.py
epquery/basicedit.py
epquery/download.py
epquery/editor.py
epquery/idd.py
epquery/idf.py
epquery/log_init.py
epquery/std.py
epquery/utilities.py
epquery/edit/__init__.py
epquery/edit/extinterface.py
epquery/edit/geometry.py
epquery/edit/internal_gains.py
epquery/edit/schedule.py
epquery-0.0.1.dist-info/DESCRIPTION.rst
epquery-0.0.1.dist-info/METADATA
epquery-0.0.1.dist-info/RECORD
epquery-0.0.1.dist-info/WHEEL
epquery-0.0.1.dist-info/metadata.json
epquery-0.0.1.dist-info/top_level.txt
