Metadata-Version: 2.0
Name: epquery
Version: 0.0.1
Summary: EnergyPlus IDF editing tool
Home-page: https://github.com/sdu-cfei/epquery
Author: Krzysztof Arendt
Author-email: krzysztof.arendt@gmail.com
License: BSD
Keywords: energyplus idf editor
Platform: Windows
Platform: Linux
Classifier: Programming Language :: Python :: 2.7
Classifier: Programming Language :: Python :: 3
Classifier: Topic :: Scientific/Engineering
Classifier: License :: OSI Approved :: BSD License
Requires-Dist: numpy
Requires-Dist: fuzzywuzzy[speedup]
Requires-Dist: requests
